mozillapulse/__init__.py
mozillapulse/config.py
mozillapulse/consumers.py
mozillapulse/publishers.py
mozillapulse/rfc3339.py
mozillapulse/utils.py
mozillapulse/messages/__init__.py
mozillapulse/messages/base.py
mozillapulse/messages/bugzilla.py
mozillapulse/messages/build.py
mozillapulse/messages/hg.py
mozillapulse/messages/test.py
MozillaPulse-1.3.dist-info/DESCRIPTION.rst
MozillaPulse-1.3.dist-info/METADATA
MozillaPulse-1.3.dist-info/metadata.json
MozillaPulse-1.3.dist-info/RECORD
MozillaPulse-1.3.dist-info/top_level.txt
MozillaPulse-1.3.dist-info/WHEEL
