Metadata-Version: 2.0
Name: MozillaPulse
Version: 1.3
Summary: Helper library for interacting with the Mozilla Pulse message system at pulse.mozilla.org
Home-page: https://hg.mozilla.org/automation/mozillapulse/
Author: Mark Cote
Author-email: mcote@mozilla.com
License: MPL 2.0
Platform: UNKNOWN
Requires-Dist: kombu
Requires-Dist: pytz
